a_pandas_ex_intersection_difference/LICENSE
a_pandas_ex_intersection_difference/README.MD
a_pandas_ex_intersection_difference/__init__.py
a_pandas_ex_intersection_difference/requirements.txt
a_pandas_ex_intersection_difference/thirdparty.json
a_pandas_ex_intersection_difference-0.1.dist-info/LICENSE.rst
a_pandas_ex_intersection_difference-0.1.dist-info/METADATA
a_pandas_ex_intersection_difference-0.1.dist-info/WHEEL
a_pandas_ex_intersection_difference-0.1.dist-info/top_level.txt
a_pandas_ex_intersection_difference-0.1.dist-info/RECORD
