Metadata-Version: 2.1
Name: a-pandas-ex-intersection-difference
Version: 0.1
Summary: Computes the intersection/symmetric difference of n DataFrames/Series
Home-page: https://github.com/hansalemaos/a_pandas_ex_intersection_difference
Author: Johannes Fischer
Author-email: <aulasparticularesdealemaosp@gmail.com>
License: MIT
Keywords: pandas,set,compare,intersection,difference
Classifier: Development Status :: 4 - Beta
Classifier: Programming Language :: Python :: 3 :: Only
Classifier: Programming Language :: Python :: 3.9
Classifier: Topic :: Scientific/Engineering :: Visualization
Classifier: Topic :: Software Development :: Libraries :: Python Modules
Classifier: Topic :: Text Editors :: Text Processing
Classifier: Topic :: Text Processing :: General
Classifier: Topic :: Text Processing :: Indexing
Classifier: Topic :: Text Processing :: Filters
Classifier: Topic :: Utilities
License-File: LICENSE.rst
Requires-Dist: a-pandas-ex-df-to-string
Requires-Dist: a-pandas-ex-plode-tool
Requires-Dist: pandas
